revealit/__init__.py
revealit/revealit.py
revealit-0.2.1.dist-info/METADATA
revealit-0.2.1.dist-info/WHEEL
revealit-0.2.1.dist-info/licenses/LICENSE
revealit-0.2.1.dist-info/RECORD
