Metadata-Version: 2.4
Name: revealit
Version: 0.2.1
Summary: Reveal variable sources in UVIT data
Project-URL: Homepage, https://github.com/prajwel/revealit
Project-URL: Issues, https://github.com/prajwel/revealit/issues
Author-email: Prajwel Joseph <prajwel.pj@gmail.com>
License-Expression: Apache-2.0
License-File: LICENSE
Classifier: Operating System :: OS Independent
Classifier: Programming Language :: Python :: 3
Requires-Python: >=3.9
Requires-Dist: astropy
Requires-Dist: matplotlib
Requires-Dist: numpy
